jonnobrows/helper/parameter_loader/__init__.py
jonnobrows/helper/parameter_loader/version.py
jonnobrows_helper_parameter_loader-0.1.0.dist-info/METADATA
jonnobrows_helper_parameter_loader-0.1.0.dist-info/WHEEL
jonnobrows_helper_parameter_loader-0.1.0.dist-info/RECORD
